{
  "type": "immersiveengineering:crusher",
  "secondaries": [
    {
      "chance": 0.1,
      "output": {
        "item": "emendatusenigmatica:silver_dust"
      },
      "conditions": [
        {
          "value": {
            "tag": "forge:dusts/silver",
            "type": "forge:tag_empty"
          },
          "type": "forge:not"
        }
      ]
    }
  ],
  "result": {
    "count": 2,
    "base_ingredient": {
      "item": "emendatusenigmatica:lead_dust"
    }
  },
  "input": {
    "tag": "forge:ores/lead"
  },
  "energy": 6000
}